odoo/addons/website_sale_attribute_filter_price/README.rst
odoo/addons/website_sale_attribute_filter_price/__init__.py
odoo/addons/website_sale_attribute_filter_price/__manifest__.py
odoo/addons/website_sale_attribute_filter_price/controllers/__init__.py
odoo/addons/website_sale_attribute_filter_price/controllers/website_sale.py
odoo/addons/website_sale_attribute_filter_price/i18n/ca.po
odoo/addons/website_sale_attribute_filter_price/i18n/es.po
odoo/addons/website_sale_attribute_filter_price/i18n/nl.po
odoo/addons/website_sale_attribute_filter_price/i18n/website_sale_attribute_filter_price.pot
odoo/addons/website_sale_attribute_filter_price/readme/CONFIGURE.rst
odoo/addons/website_sale_attribute_filter_price/readme/CONTRIBUTORS.rst
odoo/addons/website_sale_attribute_filter_price/readme/CREDITS.rst
odoo/addons/website_sale_attribute_filter_price/readme/DESCRIPTION.rst
odoo/addons/website_sale_attribute_filter_price/readme/USAGE.rst
odoo/addons/website_sale_attribute_filter_price/static/description/icon.png
odoo/addons/website_sale_attribute_filter_price/static/description/index.html
odoo/addons/website_sale_attribute_filter_price/static/src/js/shop.js
odoo/addons/website_sale_attribute_filter_price/static/src/lib/ionRangeSlider/ion.rangeSlider.css
odoo/addons/website_sale_attribute_filter_price/static/src/lib/ionRangeSlider/ion.rangeSlider.js
odoo/addons/website_sale_attribute_filter_price/templates/assets.xml
odoo/addons/website_sale_attribute_filter_price/templates/shop.xml
odoo13_addon_website_sale_attribute_filter_price-13.0.1.0.1.dist-info/METADATA
odoo13_addon_website_sale_attribute_filter_price-13.0.1.0.1.dist-info/WHEEL
odoo13_addon_website_sale_attribute_filter_price-13.0.1.0.1.dist-info/top_level.txt
odoo13_addon_website_sale_attribute_filter_price-13.0.1.0.1.dist-info/RECORD
